reprompt/__init__.py
reprompt/__main__.py
reprompt/cli.py
reprompt/client.py
reprompt/dataframe.py
reprompt/exceptions.py
reprompt/iterators.py
reprompt/transport.py
reprompt/generated/.pylintrc
reprompt/generated/__init__.py
reprompt/generated/models.py
reprompt-0.0.12.0.dist-info/entry_points.txt
reprompt-0.0.12.0.dist-info/licenses/LICENSE
reprompt-0.0.12.0.dist-info/WHEEL
reprompt-0.0.12.0.dist-info/METADATA
reprompt-0.0.12.0.dist-info/RECORD
