Metadata-Version: 2.4
Name: reprompt
Version: 0.0.12.0
Summary: Reprompt
Author-email: Lukas Martinelli <me@lukasmartinelli.ch>
Requires-Python: >=3.10
Classifier: Development Status :: 3 - Alpha
Classifier: Intended Audience :: Developers
Classifier: Programming Language :: Python :: 3 :: Only
Classifier: Programming Language :: Python :: 3.10
Classifier: Programming Language :: Python :: 3.11
Classifier: Programming Language :: Python :: 3.12
License-File: LICENSE
Requires-Dist: httpx>=0.27.0
Requires-Dist: pydantic>=2.0.0
Requires-Dist: typer>=0.12
Requires-Dist: rich>=13.7
Requires-Dist: pandas>=1.3.0 ; extra == "pandas"
Requires-Dist: pyspark>=3.0.0 ; extra == "spark"
Requires-Dist: httpx>=0.21.0 ; extra == "test"
Requires-Dist: openai>=0.10.0 ; extra == "test"
Requires-Dist: bandit[toml]==1.8.6 ; extra == "test"
Requires-Dist: black==25.1.0 ; extra == "test"
Requires-Dist: check-manifest==0.50 ; extra == "test"
Requires-Dist: flake8-bugbear==24.12.12 ; extra == "test"
Requires-Dist: flake8-docstrings ; extra == "test"
Requires-Dist: flake8-formatter_junit_xml ; extra == "test"
Requires-Dist: flake8 ; extra == "test"
Requires-Dist: flake8-pyproject ; extra == "test"
Requires-Dist: pre-commit==4.3.0 ; extra == "test"
Requires-Dist: pylint==3.3.8 ; extra == "test"
Requires-Dist: pylint_junit ; extra == "test"
Requires-Dist: pytest-cov==6.2.1 ; extra == "test"
Requires-Dist: pytest-mock<3.14.2 ; extra == "test"
Requires-Dist: pytest-runner ; extra == "test"
Requires-Dist: pytest==8.4.1 ; extra == "test"
Requires-Dist: pytest-github-actions-annotate-failures ; extra == "test"
Requires-Dist: pytest-asyncio ; extra == "test"
Requires-Dist: psutil ; extra == "test"
Requires-Dist: shellcheck-py==0.11.0.1 ; extra == "test"
Requires-Dist: openapi-generator-cli>=7.0.0 ; extra == "test"
Requires-Dist: pyright>=1.1.0 ; extra == "test"
Requires-Dist: pandas>=1.3.0 ; extra == "test"
Requires-Dist: python-dotenv>=1.0.0 ; extra == "test"
Project-URL: Documentation, https://github.com/reprompt/reprompt/tree/main#readme
Project-URL: Source, https://github.com/reprompt/reprompt
Project-URL: Tracker, https://github.com/reprompt/reprompt/issues
Provides-Extra: pandas
Provides-Extra: spark
Provides-Extra: test
